ybw/__init__.py
ybw/bin/__init__.py
ybw/bin/bin.py
ybw/get/__init__.py
ybw/get/get.py
ybw/s/__init__.py
ybw/s/s.py
ybwNB-0.0.13.dist-info/LICENSE
ybwNB-0.0.13.dist-info/METADATA
ybwNB-0.0.13.dist-info/WHEEL
ybwNB-0.0.13.dist-info/top_level.txt
ybwNB-0.0.13.dist-info/RECORD
