Metadata-Version: 2.1
Name: ybwNB
Version: 0.0.13
Summary: A small example package
Home-page: https://baidu.com
Author: ybw
Author-email: 2756456886@qq.com
License: UNKNOWN
Platform: UNKNOWN
Classifier: Programming Language :: Python :: 3
Classifier: License :: OSI Approved :: MIT License
Classifier: Operating System :: OS Independent
Requires-Python: >=3.0
